profilerpy/__init__.py
profilerpy/profiler.py
profilerpy-0.2.dist-info/LICENSE
profilerpy-0.2.dist-info/METADATA
profilerpy-0.2.dist-info/WHEEL
profilerpy-0.2.dist-info/top_level.txt
profilerpy-0.2.dist-info/RECORD
