Metadata-Version: 2.1
Name: profilerpy
Version: 0.2
Summary: A simple code profiling library.
Home-page: https://github.com/Rahgooy/profiler
Author: Taher Rahgooy
Author-email: taher.rahgooy@gmail.com
License: UNKNOWN
Platform: UNKNOWN
Requires-Python: >=3
